[
  {"probe":1,"dnsSeconds":0.000019,"tcpSeconds":0.008997,"ttfbSeconds":0.029728,"totalSeconds":0.030022,"httpCode":"200"},
  {"probe":2,"dnsSeconds":0.000015,"tcpSeconds":0.009792,"ttfbSeconds":0.031027,"totalSeconds":0.031274,"httpCode":"200"},
  {"probe":3,"dnsSeconds":0.000021,"tcpSeconds":0.009166,"ttfbSeconds":0.030049,"totalSeconds":0.030438,"httpCode":"200"},
  {"probe":4,"dnsSeconds":0.000024,"tcpSeconds":0.008965,"ttfbSeconds":0.028672,"totalSeconds":0.028947,"httpCode":"200"},
  {"probe":5,"dnsSeconds":0.000022,"tcpSeconds":0.009049,"ttfbSeconds":0.031435,"totalSeconds":0.031705,"httpCode":"200"}
]
