[
  {
    "testName": "should add a product to the cart",
    "url": "http://34.179.204.159/cart",
    "environment": "gke",
    "cloud": "gcp",
    "timestamp": "2026-05-10T08:10:59.372Z",
    "iteration": 9,
    "attemptNumber": 1,
    "passed": true,
    "nodeType": "n2-standard-2",
    "nodeCount": 2,
    "k8sVersion": "1.35",
    "clusterRegion": "europe-west3",
    "lbType": "gcp-network-lb",
    "runnerType": "cloud-build",
    "testDuration": 1035,
    "ttfb": 17.29999999998836,
    "domInteractive": 97.09999999997672,
    "domContentLoaded": 97.5,
    "loadComplete": 97.79999999998836,
    "redirectTime": 5.100000000005821,
    "dnsLookup": 0,
    "tcpConnect": 0,
    "tlsHandshake": 0,
    "serverProcessing": 10.200000000011642,
    "contentDownload": 0.7999999999883585,
    "transferSize": 16918,
    "encodedBodySize": 16618,
    "decodedBodySize": 16618,
    "resourceCount": 17,
    "totalResourceTransferSize": 0,
    "fcp": 140,
    "lcp": 140,
    "cls": 0,
    "tbt": 0,
    "inp": -1,
    "jsHeapUsed": 10000000,
    "jsHeapTotal": 10000000
  },
  {
    "testName": "should clear the cart",
    "url": "http://34.179.204.159/cart",
    "environment": "gke",
    "cloud": "gcp",
    "timestamp": "2026-05-10T08:11:01.916Z",
    "iteration": 9,
    "attemptNumber": 1,
    "passed": true,
    "nodeType": "n2-standard-2",
    "nodeCount": 2,
    "k8sVersion": "1.35",
    "clusterRegion": "europe-west3",
    "lbType": "gcp-network-lb",
    "runnerType": "cloud-build",
    "testDuration": 1864,
    "ttfb": 11.200000000011642,
    "domInteractive": 78.10000000000582,
    "domContentLoaded": 78.30000000001746,
    "loadComplete": 78.60000000000582,
    "redirectTime": 0,
    "dnsLookup": 0,
    "tcpConnect": 0,
    "tlsHandshake": 0,
    "serverProcessing": 10,
    "contentDownload": 0.6999999999825377,
    "transferSize": 7368,
    "encodedBodySize": 7068,
    "decodedBodySize": 7068,
    "resourceCount": 16,
    "totalResourceTransferSize": 0,
    "fcp": 156,
    "lcp": 156,
    "cls": 0,
    "tbt": 0,
    "inp": -1,
    "jsHeapUsed": 10000000,
    "jsHeapTotal": 11900000
  },
  {
    "testName": "should display checkout form",
    "url": "http://34.179.204.159/cart",
    "environment": "gke",
    "cloud": "gcp",
    "timestamp": "2026-05-10T08:11:03.725Z",
    "iteration": 9,
    "attemptNumber": 1,
    "passed": true,
    "nodeType": "n2-standard-2",
    "nodeCount": 2,
    "k8sVersion": "1.35",
    "clusterRegion": "europe-west3",
    "lbType": "gcp-network-lb",
    "runnerType": "cloud-build",
    "testDuration": 1042,
    "ttfb": 17.599999999976717,
    "domInteractive": 97.09999999997672,
    "domContentLoaded": 97.19999999998254,
    "loadComplete": 97.89999999999418,
    "redirectTime": 0,
    "dnsLookup": 0,
    "tcpConnect": 0,
    "tlsHandshake": 0,
    "serverProcessing": 13.199999999982538,
    "contentDownload": 0.9000000000232831,
    "transferSize": 16946,
    "encodedBodySize": 16646,
    "decodedBodySize": 16646,
    "resourceCount": 17,
    "totalResourceTransferSize": 0,
    "fcp": 104,
    "lcp": 104,
    "cls": 0,
    "tbt": 0,
    "inp": -1,
    "jsHeapUsed": 10000000,
    "jsHeapTotal": 10000000
  },
  {
    "testName": "should complete full purchase",
    "url": "http://34.179.204.159/cart/checkout",
    "environment": "gke",
    "cloud": "gcp",
    "timestamp": "2026-05-10T08:12:08.512Z",
    "iteration": 9,
    "attemptNumber": 2,
    "passed": true,
    "nodeType": "n2-standard-2",
    "nodeCount": 2,
    "k8sVersion": "1.35",
    "clusterRegion": "europe-west3",
    "lbType": "gcp-network-lb",
    "runnerType": "cloud-build",
    "testDuration": 1882,
    "ttfb": 20.10000000000582,
    "domInteractive": 85,
    "domContentLoaded": 85.10000000000582,
    "loadComplete": 85.20000000001164,
    "redirectTime": 0,
    "dnsLookup": 0,
    "tcpConnect": 0,
    "tlsHandshake": 0,
    "serverProcessing": 18.10000000000582,
    "contentDownload": 0.8000000000174623,
    "transferSize": 7309,
    "encodedBodySize": 7009,
    "decodedBodySize": 7009,
    "resourceCount": 15,
    "totalResourceTransferSize": 0,
    "fcp": 148,
    "lcp": 148,
    "cls": 0,
    "tbt": 0,
    "inp": 80,
    "jsHeapUsed": 10000000,
    "jsHeapTotal": 10600000
  },
  {
    "testName": "should load the home page and display products",
    "url": "http://34.179.204.159/",
    "environment": "gke",
    "cloud": "gcp",
    "timestamp": "2026-05-10T08:12:09.710Z",
    "iteration": 9,
    "attemptNumber": 1,
    "passed": true,
    "nodeType": "n2-standard-2",
    "nodeCount": 2,
    "k8sVersion": "1.35",
    "clusterRegion": "europe-west3",
    "lbType": "gcp-network-lb",
    "runnerType": "cloud-build",
    "testDuration": 445,
    "ttfb": 20,
    "domInteractive": 275.3999999999942,
    "domContentLoaded": 275.5,
    "loadComplete": 280,
    "redirectTime": 0,
    "dnsLookup": 0,
    "tcpConnect": 1.1000000000058208,
    "tlsHandshake": 0,
    "serverProcessing": 11.60000000000582,
    "contentDownload": 1,
    "transferSize": 11147,
    "encodedBodySize": 10847,
    "decodedBodySize": 10847,
    "resourceCount": 20,
    "totalResourceTransferSize": 924904,
    "fcp": 208,
    "lcp": 340,
    "cls": 0.191,
    "tbt": 0,
    "inp": -1,
    "jsHeapUsed": 10000000,
    "jsHeapTotal": 10000000
  },
  {
    "testName": "should navigate to product details page when a product is clicked",
    "url": "http://34.179.204.159/product/OLJCESPC7Z",
    "environment": "gke",
    "cloud": "gcp",
    "timestamp": "2026-05-10T08:12:11.026Z",
    "iteration": 9,
    "attemptNumber": 1,
    "passed": true,
    "nodeType": "n2-standard-2",
    "nodeCount": 2,
    "k8sVersion": "1.35",
    "clusterRegion": "europe-west3",
    "lbType": "gcp-network-lb",
    "runnerType": "cloud-build",
    "testDuration": 666,
    "ttfb": 12.299999999988358,
    "domInteractive": 78.89999999996508,
    "domContentLoaded": 78.89999999996508,
    "loadComplete": 93.39999999996508,
    "redirectTime": 0,
    "dnsLookup": 0,
    "tcpConnect": 0,
    "tlsHandshake": 0,
    "serverProcessing": 10.299999999988358,
    "contentDownload": 0.8999999999650754,
    "transferSize": 8424,
    "encodedBodySize": 8124,
    "decodedBodySize": 8124,
    "resourceCount": 17,
    "totalResourceTransferSize": 0,
    "fcp": 132,
    "lcp": 132,
    "cls": 0,
    "tbt": 0,
    "inp": 48,
    "jsHeapUsed": 10000000,
    "jsHeapTotal": 10000000
  }
]